vulcan/__init__.py
vulcan/api.py
vulcan/resource.py
CSGVulcan-0.3.2.dist-info/METADATA
CSGVulcan-0.3.2.dist-info/WHEEL
CSGVulcan-0.3.2.dist-info/top_level.txt
CSGVulcan-0.3.2.dist-info/RECORD
