Metadata-Version: 2.1
Name: CSGVulcan
Version: 0.3.2
Summary: A tiny library for describing data as a resource
Home-page: UNKNOWN
Author: CSG Data Science
Author-email: csgdatascience01@gmail.com
License: MIT
Platform: UNKNOWN
Classifier: License :: OSI Approved :: MIT License
Classifier: Programming Language :: Python :: 3
Classifier: Framework :: Flask
Classifier: Framework :: Setuptools Plugin
Classifier: Intended Audience :: Developers
Classifier: Topic :: Software Development :: Libraries :: Application Frameworks
Classifier: Topic :: Utilities
Classifier: Development Status :: 1 - Planning
Requires-Dist: Flask
Requires-Dist: Cython
Requires-Dist: pandas
Requires-Dist: requests
